pydantic_prompt/__init__.py
pydantic_prompt/core.py
pydantic_prompt-0.1.0.dist-info/METADATA
pydantic_prompt-0.1.0.dist-info/WHEEL
pydantic_prompt-0.1.0.dist-info/licenses/LICENSE
pydantic_prompt-0.1.0.dist-info/RECORD
