Metadata-Version: 2.4
Name: pydantic-prompt
Version: 0.1.0
Summary: Document Pydantic models for structured LLM outputs using Python docstrings
Project-URL: Homepage, https://github.com/OpenAdaptAI/PydanticPrompt
Project-URL: Bug Tracker, https://github.com/OpenAdaptAI/PydanticPrompt/issues
Author-email: Richard Abrich <richard@openadapt.ai>
License: MIT
License-File: LICENSE
Classifier: Development Status :: 4 - Beta
Classifier: Intended Audience :: Developers
Classifier: License :: OSI Approved :: MIT License
Classifier: Operating System :: OS Independent
Classifier: Programming Language :: Python :: 3
Classifier: Programming Language :: Python :: 3.11
Classifier: Programming Language :: Python :: 3.12
Classifier: Topic :: Software Development :: Libraries :: Python Modules
Requires-Python: >=3.11
Requires-Dist: pydantic>=2.0.0
Provides-Extra: dev
Requires-Dist: mypy; extra == 'dev'
Requires-Dist: pytest; extra == 'dev'
Requires-Dist: ruff; extra == 'dev'
